basicauth.py
basicauth-0.4.0.dist-info/DESCRIPTION.rst
basicauth-0.4.0.dist-info/METADATA
basicauth-0.4.0.dist-info/RECORD
basicauth-0.4.0.dist-info/WHEEL
basicauth-0.4.0.dist-info/metadata.json
basicauth-0.4.0.dist-info/top_level.txt
