Metadata-Version: 2.0
Name: basicauth
Version: 0.4.0
Summary: An incredibly simple HTTP basic auth implementation.
Home-page: https://github.com/rdegges/python-basicauth
Author: Randall Degges
Author-email: rdegges@gmail.com
License: UNLICENSE
Keywords: python security basicauth http
Platform: UNKNOWN
Classifier: License :: Public Domain
Classifier: Programming Language :: Python
Classifier: Programming Language :: Python :: 2
Classifier: Programming Language :: Python :: 2.6
Classifier: Programming Language :: Python :: 2.7
Classifier: Programming Language :: Python :: 3
Classifier: Programming Language :: Python :: 3.3
Classifier: Programming Language :: Python :: 3.4
Classifier: Programming Language :: Python :: 3.5
Classifier: Programming Language :: Python :: 3.6
Requires-Dist: six
